surprise_similarity/__init__.py
surprise_similarity/string_encoder.py
surprise_similarity/surprise_similarity.py
surprise_similarity-0.0.4.dist-info/LICENSE
surprise_similarity-0.0.4.dist-info/METADATA
surprise_similarity-0.0.4.dist-info/WHEEL
surprise_similarity-0.0.4.dist-info/top_level.txt
surprise_similarity-0.0.4.dist-info/RECORD
