Metadata-Version: 2.1
Name: surprise-similarity
Version: 0.0.4
Summary: Context-aware similarity score for embedding vectors
Home-page: https://github.com/MeetElise/surprise-similarity
Download-URL: https://github.com/MeetElise/surprise-similarity
Author: Thomas C. Bachlechner, Mario Martone, Marjorie Schillo
Author-email: thomas@eliseai.com
License: Apache 2.0
Keywords: nlp,machine learning,fewshot learning,transformers
License-File: LICENSE
Requires-Dist: datasets (>=2.3.2)
Requires-Dist: scikit-learn (>=1.0)
Requires-Dist: english-words (==1.1.0)
Requires-Dist: sentence-transformers (>=2.2.2)
Requires-Dist: pandas (>=1.4.1)
